clore_gigaspot/__init__.py
clore_gigaspot/constants.py
clore_gigaspot/logger.py
clore_gigaspot/main.py
clore_gigaspot/responses.py
gigaspot/__init__.py
gigaspot/constants.py
gigaspot/logger.py
gigaspot/main.py
gigaspot/responses.py
clore_gigaspot-0.1.4.dist-info/METADATA
clore_gigaspot-0.1.4.dist-info/WHEEL
clore_gigaspot-0.1.4.dist-info/top_level.txt
clore_gigaspot-0.1.4.dist-info/RECORD
