Metadata-Version: 2.1
Name: clore-gigaspot
Version: 0.1.4
Summary: GigaSPOT managment library
Home-page: https://gitlab.com/cloreai-public/gigaspot-python-sdk
Author: CLORE.AI
Author-email: marketing@clore.ai
Classifier: Programming Language :: Python :: 3
Classifier: License :: OSI Approved :: MIT License
Classifier: Operating System :: OS Independent
Requires-Python: >=3.9
Requires-Dist: requests (==2.32.3)
Requires-Dist: aiohttp (==3.11.11)
